_plotly_geo/__init__.py
_plotly_geo/package_data/cb_2016_us_county_500k.dbf
_plotly_geo/package_data/cb_2016_us_county_500k.shp
_plotly_geo/package_data/cb_2016_us_county_500k.shx
_plotly_geo/package_data/cb_2016_us_state_500k.dbf
_plotly_geo/package_data/cb_2016_us_state_500k.shp
_plotly_geo/package_data/cb_2016_us_state_500k.shx
_plotly_geo/package_data/gz_2010_us_050_00_500k.dbf
_plotly_geo/package_data/gz_2010_us_050_00_500k.shp
_plotly_geo/package_data/gz_2010_us_050_00_500k.shx
plotly_geo-1.0.0.dist-info/LICENSE.txt
plotly_geo-1.0.0.dist-info/METADATA
plotly_geo-1.0.0.dist-info/WHEEL
plotly_geo-1.0.0.dist-info/top_level.txt
plotly_geo-1.0.0.dist-info/RECORD
